{
  "id": "portrait_john",
  "canvas": [
    810,
    858
  ],
  "bg": "#080604",
  "windows": [
    {
      "kind": "visualizer",
      "x": 0,
      "y": 600,
      "font_px": 14,
      "bar_count": 60,
      "bar_height": 28,
      "bar_gap": 0,
      "min_freq": 60,
      "max_freq": 720,
      "magnitude": 14.0,
      "smoothing": 0.3,
      "peak_decay": 0.92,
      "peak_hold": false,
      "wave_smooth_passes": 4,
      "update_hz": 45,
      "col_dim": "#080604",
      "col_lo": "#3a2a14",
      "col_mid": "#8a6f30",
      "col_hi": "#dec070",
      "col_peak": "#ffd896",
      "col_peak_tip": "#ffffff",
      "alpha": 0.28,
      "z": 1
    },
    {
      "kind": "static",
      "path": "gallery/portrait_john_clean_blocks",
      "x": 0,
      "y": 0,
      "font_px": 6,
      "z": 5,
      "alpha": 1.0
    }
  ]
}