{"width": 36, "height": 1, "charset": "blocks", "color": "fgbg", "source": "arcana overlay", "cells": [[{"c": "T", "fg": "#c08850"}, {"c": "h", "fg": "#c08850"}, {"c": "i", "fg": "#c08850"}, {"c": "c", "fg": "#c08850"}, {"c": "k", "fg": "#c08850"}, {"c": "e", "fg": "#c08850"}, {"c": "r", "fg": "#c08850"}, {"c": " ", "fg": "#c08850"}, {"c": "T", "fg": "#c08850"}, {"c": "h", "fg": "#c08850"}, {"c": "a", "fg": "#c08850"}, {"c": "n", "fg": "#c08850"}, {"c": " ", "fg": "#c08850"}, {"c": "W", "fg": "#c08850"}, {"c": "a", "fg": "#c08850"}, {"c": "t", "fg": "#c08850"}, {"c": "e", "fg": "#c08850"}, {"c": "r", "fg": "#c08850"}, {"c": ",", "fg": "#c08850"}, {"c": " ", "fg": "#c08850"}, {"c": "S", "fg": "#c08850"}, {"c": "l", "fg": "#c08850"}, {"c": "o", "fg": "#c08850"}, {"c": "w", "fg": "#c08850"}, {"c": "e", "fg": "#c08850"}, {"c": "r", "fg": "#c08850"}, {"c": " ", "fg": "#c08850"}, {"c": "T", "fg": "#c08850"}, {"c": "h", "fg": "#c08850"}, {"c": "a", "fg": "#c08850"}, {"c": "n", "fg": "#c08850"}, {"c": " ", "fg": "#c08850"}, {"c": "T", "fg": "#c08850"}, {"c": "i", "fg": "#c08850"}, {"c": "m", "fg": "#c08850"}, {"c": "e", "fg": "#c08850"}]]}