{"width": 42, "height": 7, "charset": "blocks", "color": "fgbg", "source": "arcana overlay", "cells": [[{"c": "V", "fg": "#d8cfb0"}, {"c": "N", "fg": "#d8cfb0"}, {"c": " ", "fg": "#d8cfb0"}, {"c": "D", "fg": "#d8cfb0"}, {"c": "E", "fg": "#d8cfb0"}, {"c": "S", "fg": "#d8cfb0"}, {"c": "I", "fg": "#d8cfb0"}, {"c": "G", "fg": "#d8cfb0"}, {"c": "N", "fg": "#d8cfb0"}, {"c": " ", "fg": "#d8cfb0"}, {"c": "N", "fg": "#d8cfb0"}, {"c": "O", "fg": "#d8cfb0"}, {"c": "T", "fg": "#d8cfb0"}, {"c": "E", "fg": "#d8cfb0"}, {"c": "S", "fg": "#d8cfb0"}, {"c": ":", "fg": "#d8cfb0"}, {"c": " "}, {"c": " "}, {"c": " "}, {"c": " "}, {"c": " "}, {"c": " "}, {"c": " "}, {"c": " "}, {"c": " "}, {"c": " "}, {"c": " "}, {"c": " "}, {"c": " "}, {"c": " "}, {"c": " "}, {"c": " "}, {"c": " "}, {"c": " "}, {"c": " "}, {"c": " "}, {"c": " "}, {"c": " "}, {"c": " "}, {"c": " "}, {"c": " "}, {"c": " "}], [{"c": "E", "fg": "#d8cfb0"}, {"c": "s", "fg": "#d8cfb0"}, {"c": "t", "fg": "#d8cfb0"}, {"c": "a", "fg": "#d8cfb0"}, {"c": "b", "fg": "#d8cfb0"}, {"c": "l", "fg": "#d8cfb0"}, {"c": "i", "fg": "#d8cfb0"}, {"c": "s", "fg": "#d8cfb0"}, {"c": "h", "fg": "#d8cfb0"}, {"c": "i", "fg": "#d8cfb0"}, {"c": "n", "fg": "#d8cfb0"}, {"c": "g", "fg": "#d8cfb0"}, {"c": " ", "fg": "#d8cfb0"}, {"c": "s", "fg": "#d8cfb0"}, {"c": "h", "fg": "#d8cfb0"}, {"c": "o", "fg": "#d8cfb0"}, {"c": "t", "fg": "#d8cfb0"}, {"c": ":", "fg": "#d8cfb0"}, {"c": " ", "fg": "#d8cfb0"}, {"c": "D", "fg": "#d8cfb0"}, {"c": "'", "fg": "#d8cfb0"}, {"c": "A", "fg": "#d8cfb0"}, {"c": "m", "fg": "#d8cfb0"}, {"c": "b", "fg": "#d8cfb0"}, {"c": "r", "fg": "#d8cfb0"}, {"c": "o", "fg": "#d8cfb0"}, {"c": "s", "fg": "#d8cfb0"}, {"c": "i", "fg": "#d8cfb0"}, {"c": "o", "fg": "#d8cfb0"}, {"c": "'", "fg": "#d8cfb0"}, {"c": "s", "fg": "#d8cfb0"}, {"c": " ", "fg": "#d8cfb0"}, {"c": "i", "fg": "#d8cfb0"}, {"c": "n", "fg": "#d8cfb0"}, {"c": "t", "fg": "#d8cfb0"}, {"c": "e", "fg": "#d8cfb0"}, {"c": "r", "fg": "#d8cfb0"}, {"c": "i", "fg": "#d8cfb0"}, {"c": "o", "fg": "#d8cfb0"}, {"c": "r", "fg": "#d8cfb0"}, {"c": ",", "fg": "#d8cfb0"}, {"c": " "}], [{"c": "d", "fg": "#d8cfb0"}, {"c": "a", "fg": "#d8cfb0"}, {"c": "w", "fg": "#d8cfb0"}, {"c": "n", "fg": "#d8cfb0"}, {"c": "-", "fg": "#d8cfb0"}, {"c": "n", "fg": "#d8cfb0"}, {"c": "o", "fg": "#d8cfb0"}, {"c": "t", "fg": "#d8cfb0"}, {"c": "-", "fg": "#d8cfb0"}, {"c": "q", "fg": "#d8cfb0"}, {"c": "u", "fg": "#d8cfb0"}, {"c": "i", "fg": "#d8cfb0"}, {"c": "t", "fg": "#d8cfb0"}, {"c": "e", "fg": "#d8cfb0"}, {"c": "-", "fg": "#d8cfb0"}, {"c": "d", "fg": "#d8cfb0"}, {"c": "a", "fg": "#d8cfb0"}, {"c": "w", "fg": "#d8cfb0"}, {"c": "n", "fg": "#d8cfb0"}, {"c": " ", "fg": "#d8cfb0"}, {"c": "l", "fg": "#d8cfb0"}, {"c": "i", "fg": "#d8cfb0"}, {"c": "g", "fg": "#d8cfb0"}, {"c": "h", "fg": "#d8cfb0"}, {"c": "t", "fg": "#d8cfb0"}, {"c": "i", "fg": "#d8cfb0"}, {"c": "n", "fg": "#d8cfb0"}, {"c": "g", "fg": "#d8cfb0"}, {"c": ".", "fg": "#d8cfb0"}, {"c": " "}, {"c": " "}, {"c": " "}, {"c": " "}, {"c": " "}, {"c": " "}, {"c": " "}, {"c": " "}, {"c": " "}, {"c": " "}, {"c": " "}, {"c": " "}, {"c": " "}], [{"c": "U", "fg": "#d8cfb0"}, {"c": "I", "fg": "#d8cfb0"}, {"c": ":", "fg": "#d8cfb0"}, {"c": " ", "fg": "#d8cfb0"}, {"c": "n", "fg": "#d8cfb0"}, {"c": "o", "fg": "#d8cfb0"}, {"c": "t", "fg": "#d8cfb0"}, {"c": "e", "fg": "#d8cfb0"}, {"c": "b", "fg": "#d8cfb0"}, {"c": "o", "fg": "#d8cfb0"}, {"c": "o", "fg": "#d8cfb0"}, {"c": "k", "fg": "#d8cfb0"}, {"c": "-", "fg": "#d8cfb0"}, {"c": "a", "fg": "#d8cfb0"}, {"c": "s", "fg": "#d8cfb0"}, {"c": "-", "fg": "#d8cfb0"}, {"c": "i", "fg": "#d8cfb0"}, {"c": "n", "fg": "#d8cfb0"}, {"c": "v", "fg": "#d8cfb0"}, {"c": "e", "fg": "#d8cfb0"}, {"c": "n", "fg": "#d8cfb0"}, {"c": "t", "fg": "#d8cfb0"}, {"c": "o", "fg": "#d8cfb0"}, {"c": "r", "fg": "#d8cfb0"}, {"c": "y", "fg": "#d8cfb0"}, {"c": " ", "fg": "#d8cfb0"}, {"c": "m", "fg": "#d8cfb0"}, {"c": "e", "fg": "#d8cfb0"}, {"c": "t", "fg": "#d8cfb0"}, {"c": "a", "fg": "#d8cfb0"}, {"c": "p", "fg": "#d8cfb0"}, {"c": "h", "fg": "#d8cfb0"}, {"c": "o", "fg": "#d8cfb0"}, {"c": "r", "fg": "#d8cfb0"}, {"c": ".", "fg": "#d8cfb0"}, {"c": " "}, {"c": " "}, {"c": " "}, {"c": " "}, {"c": " "}, {"c": " "}, {"c": " "}], [{"c": "F", "fg": "#d8cfb0"}, {"c": "r", "fg": "#d8cfb0"}, {"c": "a", "fg": "#d8cfb0"}, {"c": "s", "fg": "#d8cfb0"}, {"c": "i", "fg": "#d8cfb0"}, {"c": "e", "fg": "#d8cfb0"}, {"c": "r", "fg": "#d8cfb0"}, {"c": "'", "fg": "#d8cfb0"}, {"c": "s", "fg": "#d8cfb0"}, {"c": " ", "fg": "#d8cfb0"}, {"c": "e", "fg": "#d8cfb0"}, {"c": "n", "fg": "#d8cfb0"}, {"c": "t", "fg": "#d8cfb0"}, {"c": "r", "fg": "#d8cfb0"}, {"c": "a", "fg": "#d8cfb0"}, {"c": "n", "fg": "#d8cfb0"}, {"c": "c", "fg": "#d8cfb0"}, {"c": "e", "fg": "#d8cfb0"}, {"c": " ", "fg": "#d8cfb0"}, {"c": "t", "fg": "#d8cfb0"}, {"c": "r", "fg": "#d8cfb0"}, {"c": "i", "fg": "#d8cfb0"}, {"c": "g", "fg": "#d8cfb0"}, {"c": "g", "fg": "#d8cfb0"}, {"c": "e", "fg": "#d8cfb0"}, {"c": "r", "fg": "#d8cfb0"}, {"c": "s", "fg": "#d8cfb0"}, {"c": " ", "fg": "#d8cfb0"}, {"c": "f", "fg": "#d8cfb0"}, {"c": "i", "fg": "#d8cfb0"}, {"c": "r", "fg": "#d8cfb0"}, {"c": "s", "fg": "#d8cfb0"}, {"c": "t", "fg": "#d8cfb0"}, {"c": " ", "fg": "#d8cfb0"}, {"c": "'", "fg": "#d8cfb0"}, {"c": "c", "fg": "#d8cfb0"}, {"c": "h", "fg": "#d8cfb0"}, {"c": "o", "fg": "#d8cfb0"}, {"c": "i", "fg": "#d8cfb0"}, {"c": "c", "fg": "#d8cfb0"}, {"c": "e", "fg": "#d8cfb0"}, {"c": "'", "fg": "#d8cfb0"}], [{"c": "b", "fg": "#d8cfb0"}, {"c": "e", "fg": "#d8cfb0"}, {"c": "a", "fg": "#d8cfb0"}, {"c": "t", "fg": "#d8cfb0"}, {"c": " ", "fg": "#d8cfb0"}, {"c": "\u2014", "fg": "#d8cfb0"}, {"c": " ", "fg": "#d8cfb0"}, {"c": "i", "fg": "#d8cfb0"}, {"c": "l", "fg": "#d8cfb0"}, {"c": "l", "fg": "#d8cfb0"}, {"c": "u", "fg": "#d8cfb0"}, {"c": "s", "fg": "#d8cfb0"}, {"c": "o", "fg": "#d8cfb0"}, {"c": "r", "fg": "#d8cfb0"}, {"c": "y", "fg": "#d8cfb0"}, {"c": ".", "fg": "#d8cfb0"}, {"c": " ", "fg": "#d8cfb0"}, {"c": "C", "fg": "#d8cfb0"}, {"c": "o", "fg": "#d8cfb0"}, {"c": "l", "fg": "#d8cfb0"}, {"c": "o", "fg": "#d8cfb0"}, {"c": "r", "fg": "#d8cfb0"}, {"c": " ", "fg": "#d8cfb0"}, {"c": "p", "fg": "#d8cfb0"}, {"c": "a", "fg": "#d8cfb0"}, {"c": "l", "fg": "#d8cfb0"}, {"c": "e", "fg": "#d8cfb0"}, {"c": "t", "fg": "#d8cfb0"}, {"c": "t", "fg": "#d8cfb0"}, {"c": "e", "fg": "#d8cfb0"}, {"c": ":", "fg": "#d8cfb0"}, {"c": " ", "fg": "#d8cfb0"}, {"c": "j", "fg": "#d8cfb0"}, {"c": "a", "fg": "#d8cfb0"}, {"c": "u", "fg": "#d8cfb0"}, {"c": "n", "fg": "#d8cfb0"}, {"c": "d", "fg": "#d8cfb0"}, {"c": "i", "fg": "#d8cfb0"}, {"c": "c", "fg": "#d8cfb0"}, {"c": "e", "fg": "#d8cfb0"}, {"c": "d", "fg": "#d8cfb0"}, {"c": " "}], [{"c": "f", "fg": "#d8cfb0"}, {"c": "l", "fg": "#d8cfb0"}, {"c": "u", "fg": "#d8cfb0"}, {"c": "o", "fg": "#d8cfb0"}, {"c": "r", "fg": "#d8cfb0"}, {"c": "e", "fg": "#d8cfb0"}, {"c": "s", "fg": "#d8cfb0"}, {"c": "c", "fg": "#d8cfb0"}, {"c": "e", "fg": "#d8cfb0"}, {"c": "n", "fg": "#d8cfb0"}, {"c": "t", "fg": "#d8cfb0"}, {"c": " ", "fg": "#d8cfb0"}, {"c": "y", "fg": "#d8cfb0"}, {"c": "e", "fg": "#d8cfb0"}, {"c": "l", "fg": "#d8cfb0"}, {"c": "l", "fg": "#d8cfb0"}, {"c": "o", "fg": "#d8cfb0"}, {"c": "w", "fg": "#d8cfb0"}, {"c": ",", "fg": "#d8cfb0"}, {"c": " ", "fg": "#d8cfb0"}, {"c": "b", "fg": "#d8cfb0"}, {"c": "l", "fg": "#d8cfb0"}, {"c": "u", "fg": "#d8cfb0"}, {"c": "e", "fg": "#d8cfb0"}, {"c": "-", "fg": "#d8cfb0"}, {"c": "g", "fg": "#d8cfb0"}, {"c": "r", "fg": "#d8cfb0"}, {"c": "e", "fg": "#d8cfb0"}, {"c": "y", "fg": "#d8cfb0"}, {"c": " ", "fg": "#d8cfb0"}, {"c": "s", "fg": "#d8cfb0"}, {"c": "h", "fg": "#d8cfb0"}, {"c": "a", "fg": "#d8cfb0"}, {"c": "d", "fg": "#d8cfb0"}, {"c": "o", "fg": "#d8cfb0"}, {"c": "w", "fg": "#d8cfb0"}, {"c": ".", "fg": "#d8cfb0"}, {"c": " "}, {"c": " "}, {"c": " "}, {"c": " "}, {"c": " "}]]}