{
  "scope": "judgement",
  "notes": "JUDGEMENT action cards. The ensemble verbs at the parish cemetery on All Souls' Eve: READ NAME (the central act), LIGHT CANDLE (the supportive act), LEAVE FLOWER (a small offering at a vault), RING LAMP (signal between the rows — one of the wrought-iron lamps has a brass bell-pull), WALK ROW (the procession).",
  "cards": [
    {
      "id": "read_name",
      "title": "READ NAME",
      "time_cost": 1,
      "starter": true,
      "available_in_locations": ["parish_cemetery"],
      "flavor": "At the lectern or at a vault. Stand. Open the missal. Read one name aloud. Say the dates if you have them. The ensemble keeps reading after you. The chain is the chain.",
      "requires": [{"kind": "at_any_pos", "any_of": ["central_mausoleum", "vault_row_w", "vault_row_e", "vault_row_n", "path_spine_n", "path_spine_s"]}],
      "effects": [
        {"kind": "increment_meta", "key": "names_read_count"},
        {"kind": "lose_inertia", "amount": 1},
        {"kind": "log", "text": "Name read. The ensemble registers."}
      ]
    },
    {
      "id": "light_candle",
      "title": "LIGHT CANDLE",
      "time_cost": 1,
      "starter": true,
      "available_in_locations": ["parish_cemetery"],
      "flavor": "Pick a vault. Set the small white candle on the lintel. Strike the match. Light the wick. Cup the flame against the wind until the wick takes.",
      "requires": [{"kind": "at_any_pos", "any_of": ["central_mausoleum", "vault_row_w", "vault_row_e", "vault_row_n"]}],
      "effects": [
        {"kind": "increment_meta", "key": "candles_lit_count"},
        {"kind": "lose_inertia", "amount": 2},
        {"kind": "log", "text": "Candle on the lintel. The wick caught on the second match. The flame is small."}
      ]
    },
    {
      "id": "leave_flower",
      "title": "LEAVE FLOWER",
      "time_cost": 1,
      "starter": true,
      "available_in_locations": ["parish_cemetery"],
      "flavor": "A single flower from the chapel basket at the gate. Marigolds tonight — they hold the All Souls' colour. Set it at the foot of a vault.",
      "requires": [{"kind": "at_any_pos", "any_of": ["central_mausoleum", "vault_row_w", "vault_row_e", "vault_row_n"]}],
      "effects": [
        {"kind": "lose_inertia", "amount": 1},
        {"kind": "advance_visitor_step", "target": "the_widow_at_the_mausoleum", "amount": 1},
        {"kind": "log", "text": "A marigold at the base. The wind moves the petals once. The petals stay."}
      ]
    },
    {
      "id": "ring_lamp",
      "title": "RING LAMP",
      "time_cost": 0,
      "starter": true,
      "available_in_locations": ["parish_cemetery"],
      "flavor": "The central spine's third lamp has a brass bell at its base. Pull the cord once. The bell carries to the W and E rows. The bell means a name is about to be read.",
      "requires": [{"kind": "at_pos", "pos": "lamp_central"}],
      "effects": [
        {"kind": "lose_inertia", "amount": 1},
        {"kind": "log", "text": "Bell once. The W row's reader pauses. The E row's reader looks up. The space for your reading is made."}
      ]
    },
    {
      "id": "walk_row",
      "title": "WALK ROW",
      "time_cost": 1,
      "starter": false,
      "available_in_locations": ["parish_cemetery"],
      "flavor": "End to end. Read each vault's name in your head as you pass. Do not read them aloud; that is for the lectern and for the chosen names. The walking is the body's reading.",
      "requires": [{"kind": "at_any_pos", "any_of": ["vault_row_w", "vault_row_e", "vault_row_n"]}],
      "effects": [
        {"kind": "lose_inertia", "amount": 2},
        {"kind": "increment_meta", "key": "rows_walked_count"},
        {"kind": "log", "text": "Row walked. The names register without your voice. The walking is the witness."}
      ]
    }
  ]
}
