{
  "id": "ending_warlord_of_parsa",
  "notes": "Kyrindi great hall. Coronation. Royal purple carpet, torches, a figure on the throne. Beside it, a smaller figure adjusting a crown that is slightly too small.",
  "w": 160,
  "h": 90,
  "palette": [
    "#181028",
    "#2a1c48",
    "#4a2878",
    "#f8c848",
    "#c8983a",
    "#e0d0b0",
    "#8a2050",
    "#0a0818",
    "#a0b0c8"
  ],
  "layers": [
    {
      "op": "fill",
      "color": 0
    },
    {
      "op": "hband",
      "y_range": [
        70,
        90
      ],
      "color": 1
    },
    {
      "op": "vband",
      "x_range": [
        66,
        94
      ],
      "color": 6
    },
    {
      "op": "rect",
      "xywh": [
        60,
        26,
        40,
        44
      ],
      "color": 2
    },
    {
      "op": "rect",
      "xywh": [
        70,
        20,
        20,
        10
      ],
      "color": 4
    },
    {
      "op": "rect",
      "xywh": [
        74,
        34,
        12,
        26
      ],
      "color": 7
    },
    {
      "op": "dot",
      "xy": [
        80,
        32
      ],
      "size": 5,
      "color": 5
    },
    {
      "op": "rect",
      "xywh": [
        75,
        26,
        10,
        4
      ],
      "color": 3
    },
    {
      "op": "rect",
      "xywh": [
        104,
        44,
        8,
        26
      ],
      "color": 8
    },
    {
      "op": "dot",
      "xy": [
        108,
        40
      ],
      "size": 4,
      "color": 5
    },
    {
      "op": "rect",
      "xywh": [
        105,
        36,
        7,
        3
      ],
      "color": 3
    },
    {
      "op": "polyline",
      "points": [
        [
          112,
          38
        ],
        [
          114,
          36
        ]
      ],
      "color": 5
    },
    {
      "op": "vline",
      "x": 20,
      "y_range": [
        20,
        70
      ],
      "color": 4
    },
    {
      "op": "dot",
      "xy": [
        20,
        18
      ],
      "size": 3,
      "color": 3
    },
    {
      "op": "vline",
      "x": 140,
      "y_range": [
        20,
        70
      ],
      "color": 4
    },
    {
      "op": "dot",
      "xy": [
        140,
        18
      ],
      "size": 3,
      "color": 3
    }
  ]
}